README.rst
setup.py
iterable_orm/__init__.py
iterable_orm/query.py
iterable_orm/tests.py
iterable_orm.egg-info/PKG-INFO
iterable_orm.egg-info/SOURCES.txt
iterable_orm.egg-info/dependency_links.txt
iterable_orm.egg-info/top_level.txt