Metadata-Version: 1.1
Name: iterable-orm
Version: 0.4
Summary: Query API similar to Django for Python objects and dictionaries
Home-page: https://github.com/Said007/iterable_orm
Author: Said Ali
Author-email: said.ali@msn.com
License: UNKNOWN
Platform: UNKNOWN
Classifier: Development Status :: 2 - Pre-Alpha
Classifier: Programming Language :: Python
Classifier: Programming Language :: Python :: 2
Classifier: Programming Language :: Python :: 2.7
Classifier: Programming Language :: Python :: 3
Classifier: Programming Language :: Python :: 3.4
Classifier: Programming Language :: Python :: 3.5
